{
  "kind": "page",
  "id": 39,
  "uri": "/amenities/",
  "title": "Amenities",
  "layouts": [
    {
      "acf_fc_layout": "full_bleed_img",
      "layout_settings": {
        "section_title": "",
        "section_h2": "",
        "section_text": "",
        "green_bg": false,
        "section_text_below": false
      },
      "video": [
        {
          "yt_img": {
            "ID": 83,
            "id": 83,
            "title": "RECENT SPACES",
            "filename": "park-row-amenities.jpg",
            "filesize": 444715,
            "url": "https://parkrow1.wpenginepowered.com/wp-content/uploads/2025/12/park-row-amenities.jpg",
            "link": "https://parkrow1.wpenginepowered.com/amenities/recent-spaces-3/",
            "alt": "",
            "author": "1",
            "description": "",
            "caption": "RECENT SPACES",
            "name": "recent-spaces-3",
            "status": "inherit",
            "uploaded_to": 39,
            "date": "2025-12-01 05:09:48",
            "modified": "2025-12-01 05:09:48",
            "menu_order": 0,
            "mime_type": "image/jpeg",
            "type": "image",
            "subtype": "jpeg",
            "icon": "https://parkrow1.wpenginepowered.com/wp-includes/images/media/default.png",
            "width": 1600,
            "height": 908,
            "sizes": {
              "thumbnail": "https://parkrow1.wpenginepowered.com/wp-content/uploads/2025/12/park-row-amenities-150x150.jpg",
              "thumbnail-width": 150,
              "thumbnail-height": 150,
              "medium": "https://parkrow1.wpenginepowered.com/wp-content/uploads/2025/12/park-row-amenities-300x170.jpg",
              "medium-width": 300,
              "medium-height": 170,
              "medium_large": "https://parkrow1.wpenginepowered.com/wp-content/uploads/2025/12/park-row-amenities-768x436.jpg",
              "medium_large-width": 768,
              "medium_large-height": 436,
              "large": "https://parkrow1.wpenginepowered.com/wp-content/uploads/2025/12/park-row-amenities-1024x581.jpg",
              "large-width": 1024,
              "large-height": 581,
              "1536x1536": "https://parkrow1.wpenginepowered.com/wp-content/uploads/2025/12/park-row-amenities-1536x872.jpg",
              "1536x1536-width": 1536,
              "1536x1536-height": 872,
              "2048x2048": "https://parkrow1.wpenginepowered.com/wp-content/uploads/2025/12/park-row-amenities.jpg",
              "2048x2048-width": 1600,
              "2048x2048-height": 908,
              "header_logo": "https://parkrow1.wpenginepowered.com/wp-content/uploads/2025/12/park-row-amenities-100x57.jpg",
              "header_logo-width": 100,
              "header_logo-height": 57,
              "ph": "https://parkrow1.wpenginepowered.com/wp-content/uploads/2025/12/park-row-amenities-10x6.jpg",
              "ph-width": 10,
              "ph-height": 6,
              "intch_xl": "https://parkrow1.wpenginepowered.com/wp-content/uploads/2025/12/park-row-amenities.jpg",
              "intch_xl-width": 1600,
              "intch_xl-height": 908,
              "intch_lg": "https://parkrow1.wpenginepowered.com/wp-content/uploads/2025/12/park-row-amenities-1500x851.jpg",
              "intch_lg-width": 1500,
              "intch_lg-height": 851,
              "intch_med": "https://parkrow1.wpenginepowered.com/wp-content/uploads/2025/12/park-row-amenities-1000x568.jpg",
              "intch_med-width": 1000,
              "intch_med-height": 568,
              "intch_sm": "https://parkrow1.wpenginepowered.com/wp-content/uploads/2025/12/park-row-amenities-600x341.jpg",
              "intch_sm-width": 600,
              "intch_sm-height": 341,
              "post_slide": "https://parkrow1.wpenginepowered.com/wp-content/uploads/2025/12/park-row-amenities-750x426.jpg",
              "post_slide-width": 750,
              "post_slide-height": 426,
              "post_imgcol": "https://parkrow1.wpenginepowered.com/wp-content/uploads/2025/12/park-row-amenities-400x227.jpg",
              "post_imgcol-width": 400,
              "post_imgcol-height": 227,
              "post_twocol": "https://parkrow1.wpenginepowered.com/wp-content/uploads/2025/12/park-row-amenities-440x250.jpg",
              "post_twocol-width": 440,
              "post_twocol-height": 250,
              "post_slide2x": "https://parkrow1.wpenginepowered.com/wp-content/uploads/2025/12/park-row-amenities-1500x851.jpg",
              "post_slide2x-width": 1500,
              "post_slide2x-height": 851,
              "post_imgcol2x": "https://parkrow1.wpenginepowered.com/wp-content/uploads/2025/12/park-row-amenities-800x454.jpg",
              "post_imgcol2x-width": 800,
              "post_imgcol2x-height": 454,
              "post_twocol2x": "https://parkrow1.wpenginepowered.com/wp-content/uploads/2025/12/park-row-amenities-880x499.jpg",
              "post_twocol2x-width": 880,
              "post_twocol2x-height": 499,
              "logo-slider": "https://parkrow1.wpenginepowered.com/wp-content/uploads/2025/12/park-row-amenities-529x300.jpg",
              "logo-slider-width": 529,
              "logo-slider-height": 300,
              "fav16": "https://parkrow1.wpenginepowered.com/wp-content/uploads/2025/12/park-row-amenities-16x16.jpg",
              "fav16-width": 16,
              "fav16-height": 16,
              "fav32": "https://parkrow1.wpenginepowered.com/wp-content/uploads/2025/12/park-row-amenities-32x32.jpg",
              "fav32-width": 32,
              "fav32-height": 32,
              "fav57": "https://parkrow1.wpenginepowered.com/wp-content/uploads/2025/12/park-row-amenities-57x57.jpg",
              "fav57-width": 57,
              "fav57-height": 57,
              "fav60": "https://parkrow1.wpenginepowered.com/wp-content/uploads/2025/12/park-row-amenities-60x60.jpg",
              "fav60-width": 60,
              "fav60-height": 60,
              "fav72": "https://parkrow1.wpenginepowered.com/wp-content/uploads/2025/12/park-row-amenities-72x72.jpg",
              "fav72-width": 72,
              "fav72-height": 72,
              "fav76": "https://parkrow1.wpenginepowered.com/wp-content/uploads/2025/12/park-row-amenities-76x76.jpg",
              "fav76-width": 76,
              "fav76-height": 76,
              "fav96": "https://parkrow1.wpenginepowered.com/wp-content/uploads/2025/12/park-row-amenities-96x96.jpg",
              "fav96-width": 96,
              "fav96-height": 96,
              "fav114": "https://parkrow1.wpenginepowered.com/wp-content/uploads/2025/12/park-row-amenities-114x114.jpg",
              "fav114-width": 114,
              "fav114-height": 114,
              "fav120": "https://parkrow1.wpenginepowered.com/wp-content/uploads/2025/12/park-row-amenities-120x120.jpg",
              "fav120-width": 120,
              "fav120-height": 120,
              "fav144": "https://parkrow1.wpenginepowered.com/wp-content/uploads/2025/12/park-row-amenities-144x144.jpg",
              "fav144-width": 144,
              "fav144-height": 144,
              "fav152": "https://parkrow1.wpenginepowered.com/wp-content/uploads/2025/12/park-row-amenities-152x152.jpg",
              "fav152-width": 152,
              "fav152-height": 152,
              "fav180": "https://parkrow1.wpenginepowered.com/wp-content/uploads/2025/12/park-row-amenities-180x180.jpg",
              "fav180-width": 180,
              "fav180-height": 180,
              "fav196": "https://parkrow1.wpenginepowered.com/wp-content/uploads/2025/12/park-row-amenities-196x196.jpg",
              "fav196-width": 196,
              "fav196-height": 196,
              "gb-block-post-grid-landscape": "https://parkrow1.wpenginepowered.com/wp-content/uploads/2025/12/park-row-amenities-600x400.jpg",
              "gb-block-post-grid-landscape-width": 600,
              "gb-block-post-grid-landscape-height": 400,
              "gb-block-post-grid-square": "https://parkrow1.wpenginepowered.com/wp-content/uploads/2025/12/park-row-amenities-600x600.jpg",
              "gb-block-post-grid-square-width": 600,
              "gb-block-post-grid-square-height": 600
            }
          },
          "cf_stream_video": "",
          "show_controls": false,
          "yt_hover": false,
          "yt_lb": "",
          "cf_lb": "",
          "yt_start": "",
          "yt_end": "",
          "yt_aspect": "",
          "image_align": "center"
        }
      ],
      "caption": "",
      "caption_pos": "",
      "width": "full",
      "round_corner": false,
      "corner_pos": "left",
      "align": "",
      "push": "",
      "bleed": false,
      "content": false
    },
    {
      "acf_fc_layout": "full_bleed_img",
      "layout_settings": {
        "section_title": "Gather, refresh, <br />\r\n& find balance",
        "section_h2": "25,000 sq ft of Club-inspired Lifestyle Amenities",
        "section_text": "<p>Whether it’s recreation, leisure, relaxation, or social gathering, the amenities invite residents to live fully, with dedicated spaces and programs for wellness, community and connection, or quiet reflection.</p>\n",
        "green_bg": false,
        "section_text_below": false
      },
      "video": [
        {
          "yt_img": {
            "ID": 84,
            "id": 84,
            "title": "health-club",
            "filename": "health-club.jpg",
            "filesize": 2015530,
            "url": "https://parkrow1.wpenginepowered.com/wp-content/uploads/2025/12/health-club.jpg",
            "link": "https://parkrow1.wpenginepowered.com/amenities/health-club/",
            "alt": "",
            "author": "1",
            "description": "",
            "caption": "",
            "name": "health-club",
            "status": "inherit",
            "uploaded_to": 39,
            "date": "2025-12-01 05:14:36",
            "modified": "2025-12-01 05:14:36",
            "menu_order": 0,
            "mime_type": "image/jpeg",
            "type": "image",
            "subtype": "jpeg",
            "icon": "https://parkrow1.wpenginepowered.com/wp-includes/images/media/default.png",
            "width": 2041,
            "height": 1080,
            "sizes": {
              "thumbnail": "https://parkrow1.wpenginepowered.com/wp-content/uploads/2025/12/health-club-150x150.jpg",
              "thumbnail-width": 150,
              "thumbnail-height": 150,
              "medium": "https://parkrow1.wpenginepowered.com/wp-content/uploads/2025/12/health-club-300x159.jpg",
              "medium-width": 300,
              "medium-height": 159,
              "medium_large": "https://parkrow1.wpenginepowered.com/wp-content/uploads/2025/12/health-club-768x406.jpg",
              "medium_large-width": 768,
              "medium_large-height": 406,
              "large": "https://parkrow1.wpenginepowered.com/wp-content/uploads/2025/12/health-club-1024x542.jpg",
              "large-width": 1024,
              "large-height": 542,
              "1536x1536": "https://parkrow1.wpenginepowered.com/wp-content/uploads/2025/12/health-club-1536x813.jpg",
              "1536x1536-width": 1536,
              "1536x1536-height": 813,
              "2048x2048": "https://parkrow1.wpenginepowered.com/wp-content/uploads/2025/12/health-club.jpg",
              "2048x2048-width": 2041,
              "2048x2048-height": 1080,
              "header_logo": "https://parkrow1.wpenginepowered.com/wp-content/uploads/2025/12/health-club-100x53.jpg",
              "header_logo-width": 100,
              "header_logo-height": 53,
              "ph": "https://parkrow1.wpenginepowered.com/wp-content/uploads/2025/12/health-club-10x5.jpg",
              "ph-width": 10,
              "ph-height": 5,
              "intch_xl": "https://parkrow1.wpenginepowered.com/wp-content/uploads/2025/12/health-club.jpg",
              "intch_xl-width": 2041,
              "intch_xl-height": 1080,
              "intch_lg": "https://parkrow1.wpenginepowered.com/wp-content/uploads/2025/12/health-club-1500x794.jpg",
              "intch_lg-width": 1500,
              "intch_lg-height": 794,
              "intch_med": "https://parkrow1.wpenginepowered.com/wp-content/uploads/2025/12/health-club-1000x529.jpg",
              "intch_med-width": 1000,
              "intch_med-height": 529,
              "intch_sm": "https://parkrow1.wpenginepowered.com/wp-content/uploads/2025/12/health-club-600x317.jpg",
              "intch_sm-width": 600,
              "intch_sm-height": 317,
              "post_slide": "https://parkrow1.wpenginepowered.com/wp-content/uploads/2025/12/health-club-750x397.jpg",
              "post_slide-width": 750,
              "post_slide-height": 397,
              "post_imgcol": "https://parkrow1.wpenginepowered.com/wp-content/uploads/2025/12/health-club-400x212.jpg",
              "post_imgcol-width": 400,
              "post_imgcol-height": 212,
              "post_twocol": "https://parkrow1.wpenginepowered.com/wp-content/uploads/2025/12/health-club-440x233.jpg",
              "post_twocol-width": 440,
              "post_twocol-height": 233,
              "post_slide2x": "https://parkrow1.wpenginepowered.com/wp-content/uploads/2025/12/health-club-1500x794.jpg",
              "post_slide2x-width": 1500,
              "post_slide2x-height": 794,
              "post_imgcol2x": "https://parkrow1.wpenginepowered.com/wp-content/uploads/2025/12/health-club-800x423.jpg",
              "post_imgcol2x-width": 800,
              "post_imgcol2x-height": 423,
              "post_twocol2x": "https://parkrow1.wpenginepowered.com/wp-content/uploads/2025/12/health-club-880x466.jpg",
              "post_twocol2x-width": 880,
              "post_twocol2x-height": 466,
              "logo-slider": "https://parkrow1.wpenginepowered.com/wp-content/uploads/2025/12/health-club-567x300.jpg",
              "logo-slider-width": 567,
              "logo-slider-height": 300,
              "fav16": "https://parkrow1.wpenginepowered.com/wp-content/uploads/2025/12/health-club-16x16.jpg",
              "fav16-width": 16,
              "fav16-height": 16,
              "fav32": "https://parkrow1.wpenginepowered.com/wp-content/uploads/2025/12/health-club-32x32.jpg",
              "fav32-width": 32,
              "fav32-height": 32,
              "fav57": "https://parkrow1.wpenginepowered.com/wp-content/uploads/2025/12/health-club-57x57.jpg",
              "fav57-width": 57,
              "fav57-height": 57,
              "fav60": "https://parkrow1.wpenginepowered.com/wp-content/uploads/2025/12/health-club-60x60.jpg",
              "fav60-width": 60,
              "fav60-height": 60,
              "fav72": "https://parkrow1.wpenginepowered.com/wp-content/uploads/2025/12/health-club-72x72.jpg",
              "fav72-width": 72,
              "fav72-height": 72,
              "fav76": "https://parkrow1.wpenginepowered.com/wp-content/uploads/2025/12/health-club-76x76.jpg",
              "fav76-width": 76,
              "fav76-height": 76,
              "fav96": "https://parkrow1.wpenginepowered.com/wp-content/uploads/2025/12/health-club-96x96.jpg",
              "fav96-width": 96,
              "fav96-height": 96,
              "fav114": "https://parkrow1.wpenginepowered.com/wp-content/uploads/2025/12/health-club-114x114.jpg",
              "fav114-width": 114,
              "fav114-height": 114,
              "fav120": "https://parkrow1.wpenginepowered.com/wp-content/uploads/2025/12/health-club-120x120.jpg",
              "fav120-width": 120,
              "fav120-height": 120,
              "fav144": "https://parkrow1.wpenginepowered.com/wp-content/uploads/2025/12/health-club-144x144.jpg",
              "fav144-width": 144,
              "fav144-height": 144,
              "fav152": "https://parkrow1.wpenginepowered.com/wp-content/uploads/2025/12/health-club-152x152.jpg",
              "fav152-width": 152,
              "fav152-height": 152,
              "fav180": "https://parkrow1.wpenginepowered.com/wp-content/uploads/2025/12/health-club-180x180.jpg",
              "fav180-width": 180,
              "fav180-height": 180,
              "fav196": "https://parkrow1.wpenginepowered.com/wp-content/uploads/2025/12/health-club-196x196.jpg",
              "fav196-width": 196,
              "fav196-height": 196,
              "gb-block-post-grid-landscape": "https://parkrow1.wpenginepowered.com/wp-content/uploads/2025/12/health-club-600x400.jpg",
              "gb-block-post-grid-landscape-width": 600,
              "gb-block-post-grid-landscape-height": 400,
              "gb-block-post-grid-square": "https://parkrow1.wpenginepowered.com/wp-content/uploads/2025/12/health-club-600x600.jpg",
              "gb-block-post-grid-square-width": 600,
              "gb-block-post-grid-square-height": 600
            }
          },
          "cf_stream_video": "",
          "show_controls": false,
          "yt_hover": false,
          "yt_lb": "",
          "cf_lb": "",
          "yt_start": "",
          "yt_end": "",
          "yt_aspect": "",
          "image_align": "center"
        }
      ],
      "caption": "Caption here",
      "caption_pos": "left",
      "width": "9 columns",
      "round_corner": false,
      "corner_pos": "left",
      "align": "left",
      "push": "none",
      "bleed": true,
      "content": false
    },
    {
      "acf_fc_layout": "txt_img",
      "layout_settings": {
        "section_title": "",
        "section_h2": "",
        "section_text": "",
        "green_bg": false,
        "section_text_below": false
      },
      "video": [
        {
          "yt_img": {
            "ID": 85,
            "id": 85,
            "title": "yoga-room",
            "filename": "yoga-room.jpg",
            "filesize": 1195818,
            "url": "https://parkrow1.wpenginepowered.com/wp-content/uploads/2025/12/yoga-room.jpg",
            "link": "https://parkrow1.wpenginepowered.com/amenities/yoga-room/",
            "alt": "",
            "author": "1",
            "description": "",
            "caption": "",
            "name": "yoga-room",
            "status": "inherit",
            "uploaded_to": 39,
            "date": "2025-12-01 05:15:01",
            "modified": "2025-12-01 05:15:01",
            "menu_order": 0,
            "mime_type": "image/jpeg",
            "type": "image",
            "subtype": "jpeg",
            "icon": "https://parkrow1.wpenginepowered.com/wp-includes/images/media/default.png",
            "width": 1888,
            "height": 1080,
            "sizes": {
              "thumbnail": "https://parkrow1.wpenginepowered.com/wp-content/uploads/2025/12/yoga-room-150x150.jpg",
              "thumbnail-width": 150,
              "thumbnail-height": 150,
              "medium": "https://parkrow1.wpenginepowered.com/wp-content/uploads/2025/12/yoga-room-300x172.jpg",
              "medium-width": 300,
              "medium-height": 172,
              "medium_large": "https://parkrow1.wpenginepowered.com/wp-content/uploads/2025/12/yoga-room-768x439.jpg",
              "medium_large-width": 768,
              "medium_large-height": 439,
              "large": "https://parkrow1.wpenginepowered.com/wp-content/uploads/2025/12/yoga-room-1024x586.jpg",
              "large-width": 1024,
              "large-height": 586,
              "1536x1536": "https://parkrow1.wpenginepowered.com/wp-content/uploads/2025/12/yoga-room-1536x879.jpg",
              "1536x1536-width": 1536,
              "1536x1536-height": 879,
              "2048x2048": "https://parkrow1.wpenginepowered.com/wp-content/uploads/2025/12/yoga-room.jpg",
              "2048x2048-width": 1888,
              "2048x2048-height": 1080,
              "header_logo": "https://parkrow1.wpenginepowered.com/wp-content/uploads/2025/12/yoga-room-100x57.jpg",
              "header_logo-width": 100,
              "header_logo-height": 57,
              "ph": "https://parkrow1.wpenginepowered.com/wp-content/uploads/2025/12/yoga-room-10x6.jpg",
              "ph-width": 10,
              "ph-height": 6,
              "intch_xl": "https://parkrow1.wpenginepowered.com/wp-content/uploads/2025/12/yoga-room.jpg",
              "intch_xl-width": 1888,
              "intch_xl-height": 1080,
              "intch_lg": "https://parkrow1.wpenginepowered.com/wp-content/uploads/2025/12/yoga-room-1500x858.jpg",
              "intch_lg-width": 1500,
              "intch_lg-height": 858,
              "intch_med": "https://parkrow1.wpenginepowered.com/wp-content/uploads/2025/12/yoga-room-1000x572.jpg",
              "intch_med-width": 1000,
              "intch_med-height": 572,
              "intch_sm": "https://parkrow1.wpenginepowered.com/wp-content/uploads/2025/12/yoga-room-600x343.jpg",
              "intch_sm-width": 600,
              "intch_sm-height": 343,
              "post_slide": "https://parkrow1.wpenginepowered.com/wp-content/uploads/2025/12/yoga-room-750x429.jpg",
              "post_slide-width": 750,
              "post_slide-height": 429,
              "post_imgcol": "https://parkrow1.wpenginepowered.com/wp-content/uploads/2025/12/yoga-room-400x229.jpg",
              "post_imgcol-width": 400,
              "post_imgcol-height": 229,
              "post_twocol": "https://parkrow1.wpenginepowered.com/wp-content/uploads/2025/12/yoga-room-440x252.jpg",
              "post_twocol-width": 440,
              "post_twocol-height": 252,
              "post_slide2x": "https://parkrow1.wpenginepowered.com/wp-content/uploads/2025/12/yoga-room-1500x858.jpg",
              "post_slide2x-width": 1500,
              "post_slide2x-height": 858,
              "post_imgcol2x": "https://parkrow1.wpenginepowered.com/wp-content/uploads/2025/12/yoga-room-800x458.jpg",
              "post_imgcol2x-width": 800,
              "post_imgcol2x-height": 458,
              "post_twocol2x": "https://parkrow1.wpenginepowered.com/wp-content/uploads/2025/12/yoga-room-880x503.jpg",
              "post_twocol2x-width": 880,
              "post_twocol2x-height": 503,
              "logo-slider": "https://parkrow1.wpenginepowered.com/wp-content/uploads/2025/12/yoga-room-524x300.jpg",
              "logo-slider-width": 524,
              "logo-slider-height": 300,
              "fav16": "https://parkrow1.wpenginepowered.com/wp-content/uploads/2025/12/yoga-room-16x16.jpg",
              "fav16-width": 16,
              "fav16-height": 16,
              "fav32": "https://parkrow1.wpenginepowered.com/wp-content/uploads/2025/12/yoga-room-32x32.jpg",
              "fav32-width": 32,
              "fav32-height": 32,
              "fav57": "https://parkrow1.wpenginepowered.com/wp-content/uploads/2025/12/yoga-room-57x57.jpg",
              "fav57-width": 57,
              "fav57-height": 57,
              "fav60": "https://parkrow1.wpenginepowered.com/wp-content/uploads/2025/12/yoga-room-60x60.jpg",
              "fav60-width": 60,
              "fav60-height": 60,
              "fav72": "https://parkrow1.wpenginepowered.com/wp-content/uploads/2025/12/yoga-room-72x72.jpg",
              "fav72-width": 72,
              "fav72-height": 72,
              "fav76": "https://parkrow1.wpenginepowered.com/wp-content/uploads/2025/12/yoga-room-76x76.jpg",
              "fav76-width": 76,
              "fav76-height": 76,
              "fav96": "https://parkrow1.wpenginepowered.com/wp-content/uploads/2025/12/yoga-room-96x96.jpg",
              "fav96-width": 96,
              "fav96-height": 96,
              "fav114": "https://parkrow1.wpenginepowered.com/wp-content/uploads/2025/12/yoga-room-114x114.jpg",
              "fav114-width": 114,
              "fav114-height": 114,
              "fav120": "https://parkrow1.wpenginepowered.com/wp-content/uploads/2025/12/yoga-room-120x120.jpg",
              "fav120-width": 120,
              "fav120-height": 120,
              "fav144": "https://parkrow1.wpenginepowered.com/wp-content/uploads/2025/12/yoga-room-144x144.jpg",
              "fav144-width": 144,
              "fav144-height": 144,
              "fav152": "https://parkrow1.wpenginepowered.com/wp-content/uploads/2025/12/yoga-room-152x152.jpg",
              "fav152-width": 152,
              "fav152-height": 152,
              "fav180": "https://parkrow1.wpenginepowered.com/wp-content/uploads/2025/12/yoga-room-180x180.jpg",
              "fav180-width": 180,
              "fav180-height": 180,
              "fav196": "https://parkrow1.wpenginepowered.com/wp-content/uploads/2025/12/yoga-room-196x196.jpg",
              "fav196-width": 196,
              "fav196-height": 196,
              "gb-block-post-grid-landscape": "https://parkrow1.wpenginepowered.com/wp-content/uploads/2025/12/yoga-room-600x400.jpg",
              "gb-block-post-grid-landscape-width": 600,
              "gb-block-post-grid-landscape-height": 400,
              "gb-block-post-grid-square": "https://parkrow1.wpenginepowered.com/wp-content/uploads/2025/12/yoga-room-600x600.jpg",
              "gb-block-post-grid-square-width": 600,
              "gb-block-post-grid-square-height": 600
            }
          },
          "cf_stream_video": "",
          "show_controls": false,
          "yt_hover": false,
          "yt_lb": "",
          "cf_lb": "",
          "yt_start": "",
          "yt_end": "",
          "yt_aspect": "",
          "image_align": "center"
        }
      ],
      "caption": "Yoga mats for wellness",
      "caption_pos": "right",
      "align": "right",
      "title": "Health & Wellness",
      "text": "<p>A light-filled fitness center, yoga studio, and outdoor pool framed by greenery nurture vitality and calm in equal measure.</p>\n",
      "list": "Yoga mats\r\nAromatherapy\r\nMeditation\r\nFine herbs\r\nVegan food\r\nSoy milk\r\nKale burgers"
    },
    {
      "acf_fc_layout": "curvy_image_grid",
      "layout_settings": {
        "section_title": "",
        "section_h2": "",
        "section_text": "",
        "green_bg": false,
        "section_text_below": false
      },
      "images": [
        {
          "acf_fc_layout": "image",
          "video": [
            {
              "yt_img": {
                "ID": 107,
                "id": 107,
                "title": "RECENT SPACES",
                "filename": "indoor-pool.jpg",
                "filesize": 977332,
                "url": "https://parkrow1.wpenginepowered.com/wp-content/uploads/2025/12/indoor-pool.jpg",
                "link": "https://parkrow1.wpenginepowered.com/amenities/recent-spaces-9/",
                "alt": "",
                "author": "1",
                "description": "",
                "caption": "RECENT SPACES",
                "name": "recent-spaces-9",
                "status": "inherit",
                "uploaded_to": 39,
                "date": "2025-12-01 15:03:13",
                "modified": "2025-12-01 15:03:13",
                "menu_order": 0,
                "mime_type": "image/jpeg",
                "type": "image",
                "subtype": "jpeg",
                "icon": "https://parkrow1.wpenginepowered.com/wp-includes/images/media/default.png",
                "width": 2000,
                "height": 1137,
                "sizes": {
                  "thumbnail": "https://parkrow1.wpenginepowered.com/wp-content/uploads/2025/12/indoor-pool-150x150.jpg",
                  "thumbnail-width": 150,
                  "thumbnail-height": 150,
                  "medium": "https://parkrow1.wpenginepowered.com/wp-content/uploads/2025/12/indoor-pool-300x171.jpg",
                  "medium-width": 300,
                  "medium-height": 171,
                  "medium_large": "https://parkrow1.wpenginepowered.com/wp-content/uploads/2025/12/indoor-pool-768x437.jpg",
                  "medium_large-width": 768,
                  "medium_large-height": 437,
                  "large": "https://parkrow1.wpenginepowered.com/wp-content/uploads/2025/12/indoor-pool-1024x582.jpg",
                  "large-width": 1024,
                  "large-height": 582,
                  "1536x1536": "https://parkrow1.wpenginepowered.com/wp-content/uploads/2025/12/indoor-pool-1536x873.jpg",
                  "1536x1536-width": 1536,
                  "1536x1536-height": 873,
                  "2048x2048": "https://parkrow1.wpenginepowered.com/wp-content/uploads/2025/12/indoor-pool.jpg",
                  "2048x2048-width": 2000,
                  "2048x2048-height": 1137,
                  "header_logo": "https://parkrow1.wpenginepowered.com/wp-content/uploads/2025/12/indoor-pool-100x57.jpg",
                  "header_logo-width": 100,
                  "header_logo-height": 57,
                  "ph": "https://parkrow1.wpenginepowered.com/wp-content/uploads/2025/12/indoor-pool-10x6.jpg",
                  "ph-width": 10,
                  "ph-height": 6,
                  "intch_xl": "https://parkrow1.wpenginepowered.com/wp-content/uploads/2025/12/indoor-pool.jpg",
                  "intch_xl-width": 2000,
                  "intch_xl-height": 1137,
                  "intch_lg": "https://parkrow1.wpenginepowered.com/wp-content/uploads/2025/12/indoor-pool-1500x853.jpg",
                  "intch_lg-width": 1500,
                  "intch_lg-height": 853,
                  "intch_med": "https://parkrow1.wpenginepowered.com/wp-content/uploads/2025/12/indoor-pool-1000x569.jpg",
                  "intch_med-width": 1000,
                  "intch_med-height": 569,
                  "intch_sm": "https://parkrow1.wpenginepowered.com/wp-content/uploads/2025/12/indoor-pool-600x341.jpg",
                  "intch_sm-width": 600,
                  "intch_sm-height": 341,
                  "post_slide": "https://parkrow1.wpenginepowered.com/wp-content/uploads/2025/12/indoor-pool-750x426.jpg",
                  "post_slide-width": 750,
                  "post_slide-height": 426,
                  "post_imgcol": "https://parkrow1.wpenginepowered.com/wp-content/uploads/2025/12/indoor-pool-400x227.jpg",
                  "post_imgcol-width": 400,
                  "post_imgcol-height": 227,
                  "post_twocol": "https://parkrow1.wpenginepowered.com/wp-content/uploads/2025/12/indoor-pool-440x250.jpg",
                  "post_twocol-width": 440,
                  "post_twocol-height": 250,
                  "post_slide2x": "https://parkrow1.wpenginepowered.com/wp-content/uploads/2025/12/indoor-pool-1500x853.jpg",
                  "post_slide2x-width": 1500,
                  "post_slide2x-height": 853,
                  "post_imgcol2x": "https://parkrow1.wpenginepowered.com/wp-content/uploads/2025/12/indoor-pool-800x455.jpg",
                  "post_imgcol2x-width": 800,
                  "post_imgcol2x-height": 455,
                  "post_twocol2x": "https://parkrow1.wpenginepowered.com/wp-content/uploads/2025/12/indoor-pool-880x500.jpg",
                  "post_twocol2x-width": 880,
                  "post_twocol2x-height": 500,
                  "logo-slider": "https://parkrow1.wpenginepowered.com/wp-content/uploads/2025/12/indoor-pool-528x300.jpg",
                  "logo-slider-width": 528,
                  "logo-slider-height": 300,
                  "fav16": "https://parkrow1.wpenginepowered.com/wp-content/uploads/2025/12/indoor-pool-16x16.jpg",
                  "fav16-width": 16,
                  "fav16-height": 16,
                  "fav32": "https://parkrow1.wpenginepowered.com/wp-content/uploads/2025/12/indoor-pool-32x32.jpg",
                  "fav32-width": 32,
                  "fav32-height": 32,
                  "fav57": "https://parkrow1.wpenginepowered.com/wp-content/uploads/2025/12/indoor-pool-57x57.jpg",
                  "fav57-width": 57,
                  "fav57-height": 57,
                  "fav60": "https://parkrow1.wpenginepowered.com/wp-content/uploads/2025/12/indoor-pool-60x60.jpg",
                  "fav60-width": 60,
                  "fav60-height": 60,
                  "fav72": "https://parkrow1.wpenginepowered.com/wp-content/uploads/2025/12/indoor-pool-72x72.jpg",
                  "fav72-width": 72,
                  "fav72-height": 72,
                  "fav76": "https://parkrow1.wpenginepowered.com/wp-content/uploads/2025/12/indoor-pool-76x76.jpg",
                  "fav76-width": 76,
                  "fav76-height": 76,
                  "fav96": "https://parkrow1.wpenginepowered.com/wp-content/uploads/2025/12/indoor-pool-96x96.jpg",
                  "fav96-width": 96,
                  "fav96-height": 96,
                  "fav114": "https://parkrow1.wpenginepowered.com/wp-content/uploads/2025/12/indoor-pool-114x114.jpg",
                  "fav114-width": 114,
                  "fav114-height": 114,
                  "fav120": "https://parkrow1.wpenginepowered.com/wp-content/uploads/2025/12/indoor-pool-120x120.jpg",
                  "fav120-width": 120,
                  "fav120-height": 120,
                  "fav144": "https://parkrow1.wpenginepowered.com/wp-content/uploads/2025/12/indoor-pool-144x144.jpg",
                  "fav144-width": 144,
                  "fav144-height": 144,
                  "fav152": "https://parkrow1.wpenginepowered.com/wp-content/uploads/2025/12/indoor-pool-152x152.jpg",
                  "fav152-width": 152,
                  "fav152-height": 152,
                  "fav180": "https://parkrow1.wpenginepowered.com/wp-content/uploads/2025/12/indoor-pool-180x180.jpg",
                  "fav180-width": 180,
                  "fav180-height": 180,
                  "fav196": "https://parkrow1.wpenginepowered.com/wp-content/uploads/2025/12/indoor-pool-196x196.jpg",
                  "fav196-width": 196,
                  "fav196-height": 196,
                  "gb-block-post-grid-landscape": "https://parkrow1.wpenginepowered.com/wp-content/uploads/2025/12/indoor-pool-600x400.jpg",
                  "gb-block-post-grid-landscape-width": 600,
                  "gb-block-post-grid-landscape-height": 400,
                  "gb-block-post-grid-square": "https://parkrow1.wpenginepowered.com/wp-content/uploads/2025/12/indoor-pool-600x600.jpg",
                  "gb-block-post-grid-square-width": 600,
                  "gb-block-post-grid-square-height": 600
                }
              },
              "cf_stream_video": "",
              "show_controls": false,
              "yt_hover": false,
              "yt_lb": "",
              "cf_lb": "",
              "yt_start": "",
              "yt_end": "",
              "yt_aspect": "",
              "image_align": "center"
            }
          ],
          "large": true
        },
        {
          "acf_fc_layout": "image",
          "video": [
            {
              "yt_img": {
                "ID": 109,
                "id": 109,
                "title": "pool-swimming",
                "filename": "pool-swimming.jpg",
                "filesize": 253950,
                "url": "https://parkrow1.wpenginepowered.com/wp-content/uploads/2025/12/pool-swimming.jpg",
                "link": "https://parkrow1.wpenginepowered.com/amenities/pool-swimming/",
                "alt": "",
                "author": "1",
                "description": "",
                "caption": "",
                "name": "pool-swimming",
                "status": "inherit",
                "uploaded_to": 39,
                "date": "2025-12-01 15:04:31",
                "modified": "2025-12-01 15:04:31",
                "menu_order": 0,
                "mime_type": "image/jpeg",
                "type": "image",
                "subtype": "jpeg",
                "icon": "https://parkrow1.wpenginepowered.com/wp-includes/images/media/default.png",
                "width": 332,
                "height": 420,
                "sizes": {
                  "thumbnail": "https://parkrow1.wpenginepowered.com/wp-content/uploads/2025/12/pool-swimming-150x150.jpg",
                  "thumbnail-width": 150,
                  "thumbnail-height": 150,
                  "medium": "https://parkrow1.wpenginepowered.com/wp-content/uploads/2025/12/pool-swimming-237x300.jpg",
                  "medium-width": 237,
                  "medium-height": 300,
                  "medium_large": "https://parkrow1.wpenginepowered.com/wp-content/uploads/2025/12/pool-swimming.jpg",
                  "medium_large-width": 332,
                  "medium_large-height": 420,
                  "large": "https://parkrow1.wpenginepowered.com/wp-content/uploads/2025/12/pool-swimming.jpg",
                  "large-width": 332,
                  "large-height": 420,
                  "1536x1536": "https://parkrow1.wpenginepowered.com/wp-content/uploads/2025/12/pool-swimming.jpg",
                  "1536x1536-width": 332,
                  "1536x1536-height": 420,
                  "2048x2048": "https://parkrow1.wpenginepowered.com/wp-content/uploads/2025/12/pool-swimming.jpg",
                  "2048x2048-width": 332,
                  "2048x2048-height": 420,
                  "header_logo": "https://parkrow1.wpenginepowered.com/wp-content/uploads/2025/12/pool-swimming-47x60.jpg",
                  "header_logo-width": 47,
                  "header_logo-height": 60,
                  "ph": "https://parkrow1.wpenginepowered.com/wp-content/uploads/2025/12/pool-swimming-10x13.jpg",
                  "ph-width": 10,
                  "ph-height": 13,
                  "intch_xl": "https://parkrow1.wpenginepowered.com/wp-content/uploads/2025/12/pool-swimming.jpg",
                  "intch_xl-width": 332,
                  "intch_xl-height": 420,
                  "intch_lg": "https://parkrow1.wpenginepowered.com/wp-content/uploads/2025/12/pool-swimming.jpg",
                  "intch_lg-width": 332,
                  "intch_lg-height": 420,
                  "intch_med": "https://parkrow1.wpenginepowered.com/wp-content/uploads/2025/12/pool-swimming.jpg",
                  "intch_med-width": 332,
                  "intch_med-height": 420,
                  "intch_sm": "https://parkrow1.wpenginepowered.com/wp-content/uploads/2025/12/pool-swimming.jpg",
                  "intch_sm-width": 332,
                  "intch_sm-height": 420,
                  "post_slide": "https://parkrow1.wpenginepowered.com/wp-content/uploads/2025/12/pool-swimming.jpg",
                  "post_slide-width": 332,
                  "post_slide-height": 420,
                  "post_imgcol": "https://parkrow1.wpenginepowered.com/wp-content/uploads/2025/12/pool-swimming.jpg",
                  "post_imgcol-width": 332,
                  "post_imgcol-height": 420,
                  "post_twocol": "https://parkrow1.wpenginepowered.com/wp-content/uploads/2025/12/pool-swimming.jpg",
                  "post_twocol-width": 332,
                  "post_twocol-height": 420,
                  "post_slide2x": "https://parkrow1.wpenginepowered.com/wp-content/uploads/2025/12/pool-swimming.jpg",
                  "post_slide2x-width": 332,
                  "post_slide2x-height": 420,
                  "post_imgcol2x": "https://parkrow1.wpenginepowered.com/wp-content/uploads/2025/12/pool-swimming.jpg",
                  "post_imgcol2x-width": 332,
                  "post_imgcol2x-height": 420,
                  "post_twocol2x": "https://parkrow1.wpenginepowered.com/wp-content/uploads/2025/12/pool-swimming.jpg",
                  "post_twocol2x-width": 332,
                  "post_twocol2x-height": 420,
                  "logo-slider": "https://parkrow1.wpenginepowered.com/wp-content/uploads/2025/12/pool-swimming-237x300.jpg",
                  "logo-slider-width": 237,
                  "logo-slider-height": 300,
                  "fav16": "https://parkrow1.wpenginepowered.com/wp-content/uploads/2025/12/pool-swimming-16x16.jpg",
                  "fav16-width": 16,
                  "fav16-height": 16,
                  "fav32": "https://parkrow1.wpenginepowered.com/wp-content/uploads/2025/12/pool-swimming-32x32.jpg",
                  "fav32-width": 32,
                  "fav32-height": 32,
                  "fav57": "https://parkrow1.wpenginepowered.com/wp-content/uploads/2025/12/pool-swimming-57x57.jpg",
                  "fav57-width": 57,
                  "fav57-height": 57,
                  "fav60": "https://parkrow1.wpenginepowered.com/wp-content/uploads/2025/12/pool-swimming-60x60.jpg",
                  "fav60-width": 60,
                  "fav60-height": 60,
                  "fav72": "https://parkrow1.wpenginepowered.com/wp-content/uploads/2025/12/pool-swimming-72x72.jpg",
                  "fav72-width": 72,
                  "fav72-height": 72,
                  "fav76": "https://parkrow1.wpenginepowered.com/wp-content/uploads/2025/12/pool-swimming-76x76.jpg",
                  "fav76-width": 76,
                  "fav76-height": 76,
                  "fav96": "https://parkrow1.wpenginepowered.com/wp-content/uploads/2025/12/pool-swimming-96x96.jpg",
                  "fav96-width": 96,
                  "fav96-height": 96,
                  "fav114": "https://parkrow1.wpenginepowered.com/wp-content/uploads/2025/12/pool-swimming-114x114.jpg",
                  "fav114-width": 114,
                  "fav114-height": 114,
                  "fav120": "https://parkrow1.wpenginepowered.com/wp-content/uploads/2025/12/pool-swimming-120x120.jpg",
                  "fav120-width": 120,
                  "fav120-height": 120,
                  "fav144": "https://parkrow1.wpenginepowered.com/wp-content/uploads/2025/12/pool-swimming-144x144.jpg",
                  "fav144-width": 144,
                  "fav144-height": 144,
                  "fav152": "https://parkrow1.wpenginepowered.com/wp-content/uploads/2025/12/pool-swimming-152x152.jpg",
                  "fav152-width": 152,
                  "fav152-height": 152,
                  "fav180": "https://parkrow1.wpenginepowered.com/wp-content/uploads/2025/12/pool-swimming-180x180.jpg",
                  "fav180-width": 180,
                  "fav180-height": 180,
                  "fav196": "https://parkrow1.wpenginepowered.com/wp-content/uploads/2025/12/pool-swimming-196x196.jpg",
                  "fav196-width": 196,
                  "fav196-height": 196,
                  "gb-block-post-grid-landscape": "https://parkrow1.wpenginepowered.com/wp-content/uploads/2025/12/pool-swimming-332x400.jpg",
                  "gb-block-post-grid-landscape-width": 332,
                  "gb-block-post-grid-landscape-height": 400,
                  "gb-block-post-grid-square": "https://parkrow1.wpenginepowered.com/wp-content/uploads/2025/12/pool-swimming.jpg",
                  "gb-block-post-grid-square-width": 332,
                  "gb-block-post-grid-square-height": 420
                }
              },
              "cf_stream_video": "https://customer-u7ssw6pfj8oowdhj.cloudflarestream.com/66b34d8b22b2c127f4d970d41ea5b9c3/manifest/video.m3u8",
              "show_controls": false,
              "yt_hover": false,
              "yt_lb": "",
              "cf_lb": "",
              "yt_start": "",
              "yt_end": "",
              "yt_aspect": "",
              "image_align": "center"
            }
          ],
          "large": false
        },
        {
          "acf_fc_layout": "image",
          "video": [
            {
              "yt_img": {
                "ID": 108,
                "id": 108,
                "title": "RECENT SPACES",
                "filename": "pool-lounge.jpg",
                "filesize": 1102821,
                "url": "https://parkrow1.wpenginepowered.com/wp-content/uploads/2025/12/pool-lounge.jpg",
                "link": "https://parkrow1.wpenginepowered.com/amenities/recent-spaces-10/",
                "alt": "",
                "author": "1",
                "description": "",
                "caption": "RECENT SPACES",
                "name": "recent-spaces-10",
                "status": "inherit",
                "uploaded_to": 39,
                "date": "2025-12-01 15:03:46",
                "modified": "2025-12-01 15:03:46",
                "menu_order": 0,
                "mime_type": "image/jpeg",
                "type": "image",
                "subtype": "jpeg",
                "icon": "https://parkrow1.wpenginepowered.com/wp-includes/images/media/default.png",
                "width": 1600,
                "height": 2000,
                "sizes": {
                  "thumbnail": "https://parkrow1.wpenginepowered.com/wp-content/uploads/2025/12/pool-lounge-150x150.jpg",
                  "thumbnail-width": 150,
                  "thumbnail-height": 150,
                  "medium": "https://parkrow1.wpenginepowered.com/wp-content/uploads/2025/12/pool-lounge-240x300.jpg",
                  "medium-width": 240,
                  "medium-height": 300,
                  "medium_large": "https://parkrow1.wpenginepowered.com/wp-content/uploads/2025/12/pool-lounge-768x960.jpg",
                  "medium_large-width": 768,
                  "medium_large-height": 960,
                  "large": "https://parkrow1.wpenginepowered.com/wp-content/uploads/2025/12/pool-lounge-819x1024.jpg",
                  "large-width": 819,
                  "large-height": 1024,
                  "1536x1536": "https://parkrow1.wpenginepowered.com/wp-content/uploads/2025/12/pool-lounge-1229x1536.jpg",
                  "1536x1536-width": 1229,
                  "1536x1536-height": 1536,
                  "2048x2048": "https://parkrow1.wpenginepowered.com/wp-content/uploads/2025/12/pool-lounge.jpg",
                  "2048x2048-width": 1600,
                  "2048x2048-height": 2000,
                  "header_logo": "https://parkrow1.wpenginepowered.com/wp-content/uploads/2025/12/pool-lounge-48x60.jpg",
                  "header_logo-width": 48,
                  "header_logo-height": 60,
                  "ph": "https://parkrow1.wpenginepowered.com/wp-content/uploads/2025/12/pool-lounge-10x13.jpg",
                  "ph-width": 10,
                  "ph-height": 13,
                  "intch_xl": "https://parkrow1.wpenginepowered.com/wp-content/uploads/2025/12/pool-lounge.jpg",
                  "intch_xl-width": 1600,
                  "intch_xl-height": 2000,
                  "intch_lg": "https://parkrow1.wpenginepowered.com/wp-content/uploads/2025/12/pool-lounge-1500x1875.jpg",
                  "intch_lg-width": 1500,
                  "intch_lg-height": 1875,
                  "intch_med": "https://parkrow1.wpenginepowered.com/wp-content/uploads/2025/12/pool-lounge-1000x1250.jpg",
                  "intch_med-width": 1000,
                  "intch_med-height": 1250,
                  "intch_sm": "https://parkrow1.wpenginepowered.com/wp-content/uploads/2025/12/pool-lounge-600x750.jpg",
                  "intch_sm-width": 600,
                  "intch_sm-height": 750,
                  "post_slide": "https://parkrow1.wpenginepowered.com/wp-content/uploads/2025/12/pool-lounge-750x938.jpg",
                  "post_slide-width": 750,
                  "post_slide-height": 938,
                  "post_imgcol": "https://parkrow1.wpenginepowered.com/wp-content/uploads/2025/12/pool-lounge-400x500.jpg",
                  "post_imgcol-width": 400,
                  "post_imgcol-height": 500,
                  "post_twocol": "https://parkrow1.wpenginepowered.com/wp-content/uploads/2025/12/pool-lounge-440x550.jpg",
                  "post_twocol-width": 440,
                  "post_twocol-height": 550,
                  "post_slide2x": "https://parkrow1.wpenginepowered.com/wp-content/uploads/2025/12/pool-lounge-1500x1875.jpg",
                  "post_slide2x-width": 1500,
                  "post_slide2x-height": 1875,
                  "post_imgcol2x": "https://parkrow1.wpenginepowered.com/wp-content/uploads/2025/12/pool-lounge-800x1000.jpg",
                  "post_imgcol2x-width": 800,
                  "post_imgcol2x-height": 1000,
                  "post_twocol2x": "https://parkrow1.wpenginepowered.com/wp-content/uploads/2025/12/pool-lounge-880x1100.jpg",
                  "post_twocol2x-width": 880,
                  "post_twocol2x-height": 1100,
                  "logo-slider": "https://parkrow1.wpenginepowered.com/wp-content/uploads/2025/12/pool-lounge-240x300.jpg",
                  "logo-slider-width": 240,
                  "logo-slider-height": 300,
                  "fav16": "https://parkrow1.wpenginepowered.com/wp-content/uploads/2025/12/pool-lounge-16x16.jpg",
                  "fav16-width": 16,
                  "fav16-height": 16,
                  "fav32": "https://parkrow1.wpenginepowered.com/wp-content/uploads/2025/12/pool-lounge-32x32.jpg",
                  "fav32-width": 32,
                  "fav32-height": 32,
                  "fav57": "https://parkrow1.wpenginepowered.com/wp-content/uploads/2025/12/pool-lounge-57x57.jpg",
                  "fav57-width": 57,
                  "fav57-height": 57,
                  "fav60": "https://parkrow1.wpenginepowered.com/wp-content/uploads/2025/12/pool-lounge-60x60.jpg",
                  "fav60-width": 60,
                  "fav60-height": 60,
                  "fav72": "https://parkrow1.wpenginepowered.com/wp-content/uploads/2025/12/pool-lounge-72x72.jpg",
                  "fav72-width": 72,
                  "fav72-height": 72,
                  "fav76": "https://parkrow1.wpenginepowered.com/wp-content/uploads/2025/12/pool-lounge-76x76.jpg",
                  "fav76-width": 76,
                  "fav76-height": 76,
                  "fav96": "https://parkrow1.wpenginepowered.com/wp-content/uploads/2025/12/pool-lounge-96x96.jpg",
                  "fav96-width": 96,
                  "fav96-height": 96,
                  "fav114": "https://parkrow1.wpenginepowered.com/wp-content/uploads/2025/12/pool-lounge-114x114.jpg",
                  "fav114-width": 114,
                  "fav114-height": 114,
                  "fav120": "https://parkrow1.wpenginepowered.com/wp-content/uploads/2025/12/pool-lounge-120x120.jpg",
                  "fav120-width": 120,
                  "fav120-height": 120,
                  "fav144": "https://parkrow1.wpenginepowered.com/wp-content/uploads/2025/12/pool-lounge-144x144.jpg",
                  "fav144-width": 144,
                  "fav144-height": 144,
                  "fav152": "https://parkrow1.wpenginepowered.com/wp-content/uploads/2025/12/pool-lounge-152x152.jpg",
                  "fav152-width": 152,
                  "fav152-height": 152,
                  "fav180": "https://parkrow1.wpenginepowered.com/wp-content/uploads/2025/12/pool-lounge-180x180.jpg",
                  "fav180-width": 180,
                  "fav180-height": 180,
                  "fav196": "https://parkrow1.wpenginepowered.com/wp-content/uploads/2025/12/pool-lounge-196x196.jpg",
                  "fav196-width": 196,
                  "fav196-height": 196,
                  "gb-block-post-grid-landscape": "https://parkrow1.wpenginepowered.com/wp-content/uploads/2025/12/pool-lounge-600x400.jpg",
                  "gb-block-post-grid-landscape-width": 600,
                  "gb-block-post-grid-landscape-height": 400,
                  "gb-block-post-grid-square": "https://parkrow1.wpenginepowered.com/wp-content/uploads/2025/12/pool-lounge-600x600.jpg",
                  "gb-block-post-grid-square-width": 600,
                  "gb-block-post-grid-square-height": 600
                }
              },
              "cf_stream_video": "",
              "show_controls": false,
              "yt_hover": false,
              "yt_lb": "",
              "cf_lb": "",
              "yt_start": "",
              "yt_end": "",
              "yt_aspect": "",
              "image_align": "center"
            }
          ],
          "large": false
        }
      ],
      "caption": "A caption about pools and spas",
      "caption_pos": "left",
      "align": "left",
      "title": "Retreat & Relax",
      "text": "<p>From sauna to steam, lounge to sun deck, Park Row provides restorative spaces for body and mind.</p>\n",
      "list": "Pool toys\r\nSauna\r\nSteam room\r\nSalt water\r\nFresh water",
      "text_align": "bottom"
    },
    {
      "acf_fc_layout": "full_bleed_img",
      "layout_settings": {
        "section_title": "",
        "section_h2": "",
        "section_text": "",
        "green_bg": false,
        "section_text_below": false
      },
      "video": [
        {
          "yt_img": {
            "ID": 87,
            "id": 87,
            "title": "RECENT SPACES",
            "filename": "amenities-social-scaled.jpg",
            "filesize": 3321710,
            "url": "https://parkrow1.wpenginepowered.com/wp-content/uploads/2025/12/amenities-social-scaled.jpg",
            "link": "https://parkrow1.wpenginepowered.com/amenities/recent-spaces-5/",
            "alt": "",
            "author": "1",
            "description": "",
            "caption": "windows with apartment",
            "name": "recent-spaces-5",
            "status": "inherit",
            "uploaded_to": 39,
            "date": "2025-12-01 05:24:19",
            "modified": "2025-12-02 01:22:10",
            "menu_order": 0,
            "mime_type": "image/jpeg",
            "type": "image",
            "subtype": "jpeg",
            "icon": "https://parkrow1.wpenginepowered.com/wp-includes/images/media/default.png",
            "width": 2560,
            "height": 1439,
            "sizes": {
              "thumbnail": "https://parkrow1.wpenginepowered.com/wp-content/uploads/2025/12/amenities-social-150x150.jpg",
              "thumbnail-width": 150,
              "thumbnail-height": 150,
              "medium": "https://parkrow1.wpenginepowered.com/wp-content/uploads/2025/12/amenities-social-300x169.jpg",
              "medium-width": 300,
              "medium-height": 169,
              "medium_large": "https://parkrow1.wpenginepowered.com/wp-content/uploads/2025/12/amenities-social-768x432.jpg",
              "medium_large-width": 768,
              "medium_large-height": 432,
              "large": "https://parkrow1.wpenginepowered.com/wp-content/uploads/2025/12/amenities-social-1024x575.jpg",
              "large-width": 1024,
              "large-height": 575,
              "1536x1536": "https://parkrow1.wpenginepowered.com/wp-content/uploads/2025/12/amenities-social-1536x863.jpg",
              "1536x1536-width": 1536,
              "1536x1536-height": 863,
              "2048x2048": "https://parkrow1.wpenginepowered.com/wp-content/uploads/2025/12/amenities-social-2048x1151.jpg",
              "2048x2048-width": 2048,
              "2048x2048-height": 1151,
              "header_logo": "https://parkrow1.wpenginepowered.com/wp-content/uploads/2025/12/amenities-social-100x56.jpg",
              "header_logo-width": 100,
              "header_logo-height": 56,
              "ph": "https://parkrow1.wpenginepowered.com/wp-content/uploads/2025/12/amenities-social-10x6.jpg",
              "ph-width": 10,
              "ph-height": 6,
              "intch_xl": "https://parkrow1.wpenginepowered.com/wp-content/uploads/2025/12/amenities-social-scaled.jpg",
              "intch_xl-width": 2560,
              "intch_xl-height": 1439,
              "intch_lg": "https://parkrow1.wpenginepowered.com/wp-content/uploads/2025/12/amenities-social-1500x843.jpg",
              "intch_lg-width": 1500,
              "intch_lg-height": 843,
              "intch_med": "https://parkrow1.wpenginepowered.com/wp-content/uploads/2025/12/amenities-social-1000x562.jpg",
              "intch_med-width": 1000,
              "intch_med-height": 562,
              "intch_sm": "https://parkrow1.wpenginepowered.com/wp-content/uploads/2025/12/amenities-social-600x337.jpg",
              "intch_sm-width": 600,
              "intch_sm-height": 337,
              "post_slide": "https://parkrow1.wpenginepowered.com/wp-content/uploads/2025/12/amenities-social-750x422.jpg",
              "post_slide-width": 750,
              "post_slide-height": 422,
              "post_imgcol": "https://parkrow1.wpenginepowered.com/wp-content/uploads/2025/12/amenities-social-400x225.jpg",
              "post_imgcol-width": 400,
              "post_imgcol-height": 225,
              "post_twocol": "https://parkrow1.wpenginepowered.com/wp-content/uploads/2025/12/amenities-social-440x247.jpg",
              "post_twocol-width": 440,
              "post_twocol-height": 247,
              "post_slide2x": "https://parkrow1.wpenginepowered.com/wp-content/uploads/2025/12/amenities-social-1500x843.jpg",
              "post_slide2x-width": 1500,
              "post_slide2x-height": 843,
              "post_imgcol2x": "https://parkrow1.wpenginepowered.com/wp-content/uploads/2025/12/amenities-social-800x450.jpg",
              "post_imgcol2x-width": 800,
              "post_imgcol2x-height": 450,
              "post_twocol2x": "https://parkrow1.wpenginepowered.com/wp-content/uploads/2025/12/amenities-social-880x495.jpg",
              "post_twocol2x-width": 880,
              "post_twocol2x-height": 495,
              "logo-slider": "https://parkrow1.wpenginepowered.com/wp-content/uploads/2025/12/amenities-social-534x300.jpg",
              "logo-slider-width": 534,
              "logo-slider-height": 300,
              "fav16": "https://parkrow1.wpenginepowered.com/wp-content/uploads/2025/12/amenities-social-16x16.jpg",
              "fav16-width": 16,
              "fav16-height": 16,
              "fav32": "https://parkrow1.wpenginepowered.com/wp-content/uploads/2025/12/amenities-social-32x32.jpg",
              "fav32-width": 32,
              "fav32-height": 32,
              "fav57": "https://parkrow1.wpenginepowered.com/wp-content/uploads/2025/12/amenities-social-57x57.jpg",
              "fav57-width": 57,
              "fav57-height": 57,
              "fav60": "https://parkrow1.wpenginepowered.com/wp-content/uploads/2025/12/amenities-social-60x60.jpg",
              "fav60-width": 60,
              "fav60-height": 60,
              "fav72": "https://parkrow1.wpenginepowered.com/wp-content/uploads/2025/12/amenities-social-72x72.jpg",
              "fav72-width": 72,
              "fav72-height": 72,
              "fav76": "https://parkrow1.wpenginepowered.com/wp-content/uploads/2025/12/amenities-social-76x76.jpg",
              "fav76-width": 76,
              "fav76-height": 76,
              "fav96": "https://parkrow1.wpenginepowered.com/wp-content/uploads/2025/12/amenities-social-96x96.jpg",
              "fav96-width": 96,
              "fav96-height": 96,
              "fav114": "https://parkrow1.wpenginepowered.com/wp-content/uploads/2025/12/amenities-social-114x114.jpg",
              "fav114-width": 114,
              "fav114-height": 114,
              "fav120": "https://parkrow1.wpenginepowered.com/wp-content/uploads/2025/12/amenities-social-120x120.jpg",
              "fav120-width": 120,
              "fav120-height": 120,
              "fav144": "https://parkrow1.wpenginepowered.com/wp-content/uploads/2025/12/amenities-social-144x144.jpg",
              "fav144-width": 144,
              "fav144-height": 144,
              "fav152": "https://parkrow1.wpenginepowered.com/wp-content/uploads/2025/12/amenities-social-152x152.jpg",
              "fav152-width": 152,
              "fav152-height": 152,
              "fav180": "https://parkrow1.wpenginepowered.com/wp-content/uploads/2025/12/amenities-social-180x180.jpg",
              "fav180-width": 180,
              "fav180-height": 180,
              "fav196": "https://parkrow1.wpenginepowered.com/wp-content/uploads/2025/12/amenities-social-196x196.jpg",
              "fav196-width": 196,
              "fav196-height": 196,
              "gb-block-post-grid-landscape": "https://parkrow1.wpenginepowered.com/wp-content/uploads/2025/12/amenities-social-600x400.jpg",
              "gb-block-post-grid-landscape-width": 600,
              "gb-block-post-grid-landscape-height": 400,
              "gb-block-post-grid-square": "https://parkrow1.wpenginepowered.com/wp-content/uploads/2025/12/amenities-social-600x600.jpg",
              "gb-block-post-grid-square-width": 600,
              "gb-block-post-grid-square-height": 600
            }
          },
          "cf_stream_video": "",
          "show_controls": false,
          "yt_hover": false,
          "yt_lb": "",
          "cf_lb": "",
          "yt_start": "",
          "yt_end": "",
          "yt_aspect": "",
          "image_align": "center"
        }
      ],
      "caption": "Caption text here",
      "caption_pos": "left",
      "width": "10 columns",
      "round_corner": true,
      "corner_pos": "left",
      "align": "center",
      "push": "",
      "bleed": false,
      "content": [
        {
          "title": "Social Gathering & Community",
          "text": "<p>Elegant lounges, landscaped terraces, and private dining rooms designed for connection—celebrating Bellevue’s gracious way of life.</p>\n",
          "two_col_list": false,
          "list": ""
        },
        {
          "title": "",
          "text": "",
          "two_col_list": false,
          "list": "Detail list\r\nMicrowave\r\nOven\r\nGas stove\r\nHot showers\r\nTowels\r\nFree parking"
        }
      ]
    },
    {
      "acf_fc_layout": "full_bleed_img",
      "layout_settings": {
        "section_title": "",
        "section_h2": "",
        "section_text": "",
        "green_bg": false,
        "section_text_below": false
      },
      "video": [
        {
          "yt_img": {
            "ID": 88,
            "id": 88,
            "title": "RECENT SPACES",
            "filename": "private-dining-scaled.jpg",
            "filesize": 3923019,
            "url": "https://parkrow1.wpenginepowered.com/wp-content/uploads/2025/12/private-dining-scaled.jpg",
            "link": "https://parkrow1.wpenginepowered.com/amenities/recent-spaces-6/",
            "alt": "",
            "author": "1",
            "description": "",
            "caption": "RECENT SPACES",
            "name": "recent-spaces-6",
            "status": "inherit",
            "uploaded_to": 39,
            "date": "2025-12-01 05:27:48",
            "modified": "2025-12-01 05:27:48",
            "menu_order": 0,
            "mime_type": "image/jpeg",
            "type": "image",
            "subtype": "jpeg",
            "icon": "https://parkrow1.wpenginepowered.com/wp-includes/images/media/default.png",
            "width": 2560,
            "height": 1476,
            "sizes": {
              "thumbnail": "https://parkrow1.wpenginepowered.com/wp-content/uploads/2025/12/private-dining-150x150.jpg",
              "thumbnail-width": 150,
              "thumbnail-height": 150,
              "medium": "https://parkrow1.wpenginepowered.com/wp-content/uploads/2025/12/private-dining-300x173.jpg",
              "medium-width": 300,
              "medium-height": 173,
              "medium_large": "https://parkrow1.wpenginepowered.com/wp-content/uploads/2025/12/private-dining-768x443.jpg",
              "medium_large-width": 768,
              "medium_large-height": 443,
              "large": "https://parkrow1.wpenginepowered.com/wp-content/uploads/2025/12/private-dining-1024x591.jpg",
              "large-width": 1024,
              "large-height": 591,
              "1536x1536": "https://parkrow1.wpenginepowered.com/wp-content/uploads/2025/12/private-dining-1536x886.jpg",
              "1536x1536-width": 1536,
              "1536x1536-height": 886,
              "2048x2048": "https://parkrow1.wpenginepowered.com/wp-content/uploads/2025/12/private-dining-2048x1181.jpg",
              "2048x2048-width": 2048,
              "2048x2048-height": 1181,
              "header_logo": "https://parkrow1.wpenginepowered.com/wp-content/uploads/2025/12/private-dining-100x58.jpg",
              "header_logo-width": 100,
              "header_logo-height": 58,
              "ph": "https://parkrow1.wpenginepowered.com/wp-content/uploads/2025/12/private-dining-10x6.jpg",
              "ph-width": 10,
              "ph-height": 6,
              "intch_xl": "https://parkrow1.wpenginepowered.com/wp-content/uploads/2025/12/private-dining-scaled.jpg",
              "intch_xl-width": 2560,
              "intch_xl-height": 1476,
              "intch_lg": "https://parkrow1.wpenginepowered.com/wp-content/uploads/2025/12/private-dining-1500x865.jpg",
              "intch_lg-width": 1500,
              "intch_lg-height": 865,
              "intch_med": "https://parkrow1.wpenginepowered.com/wp-content/uploads/2025/12/private-dining-1000x577.jpg",
              "intch_med-width": 1000,
              "intch_med-height": 577,
              "intch_sm": "https://parkrow1.wpenginepowered.com/wp-content/uploads/2025/12/private-dining-600x346.jpg",
              "intch_sm-width": 600,
              "intch_sm-height": 346,
              "post_slide": "https://parkrow1.wpenginepowered.com/wp-content/uploads/2025/12/private-dining-750x433.jpg",
              "post_slide-width": 750,
              "post_slide-height": 433,
              "post_imgcol": "https://parkrow1.wpenginepowered.com/wp-content/uploads/2025/12/private-dining-400x231.jpg",
              "post_imgcol-width": 400,
              "post_imgcol-height": 231,
              "post_twocol": "https://parkrow1.wpenginepowered.com/wp-content/uploads/2025/12/private-dining-440x254.jpg",
              "post_twocol-width": 440,
              "post_twocol-height": 254,
              "post_slide2x": "https://parkrow1.wpenginepowered.com/wp-content/uploads/2025/12/private-dining-1500x865.jpg",
              "post_slide2x-width": 1500,
              "post_slide2x-height": 865,
              "post_imgcol2x": "https://parkrow1.wpenginepowered.com/wp-content/uploads/2025/12/private-dining-800x461.jpg",
              "post_imgcol2x-width": 800,
              "post_imgcol2x-height": 461,
              "post_twocol2x": "https://parkrow1.wpenginepowered.com/wp-content/uploads/2025/12/private-dining-880x507.jpg",
              "post_twocol2x-width": 880,
              "post_twocol2x-height": 507,
              "logo-slider": "https://parkrow1.wpenginepowered.com/wp-content/uploads/2025/12/private-dining-520x300.jpg",
              "logo-slider-width": 520,
              "logo-slider-height": 300,
              "fav16": "https://parkrow1.wpenginepowered.com/wp-content/uploads/2025/12/private-dining-16x16.jpg",
              "fav16-width": 16,
              "fav16-height": 16,
              "fav32": "https://parkrow1.wpenginepowered.com/wp-content/uploads/2025/12/private-dining-32x32.jpg",
              "fav32-width": 32,
              "fav32-height": 32,
              "fav57": "https://parkrow1.wpenginepowered.com/wp-content/uploads/2025/12/private-dining-57x57.jpg",
              "fav57-width": 57,
              "fav57-height": 57,
              "fav60": "https://parkrow1.wpenginepowered.com/wp-content/uploads/2025/12/private-dining-60x60.jpg",
              "fav60-width": 60,
              "fav60-height": 60,
              "fav72": "https://parkrow1.wpenginepowered.com/wp-content/uploads/2025/12/private-dining-72x72.jpg",
              "fav72-width": 72,
              "fav72-height": 72,
              "fav76": "https://parkrow1.wpenginepowered.com/wp-content/uploads/2025/12/private-dining-76x76.jpg",
              "fav76-width": 76,
              "fav76-height": 76,
              "fav96": "https://parkrow1.wpenginepowered.com/wp-content/uploads/2025/12/private-dining-96x96.jpg",
              "fav96-width": 96,
              "fav96-height": 96,
              "fav114": "https://parkrow1.wpenginepowered.com/wp-content/uploads/2025/12/private-dining-114x114.jpg",
              "fav114-width": 114,
              "fav114-height": 114,
              "fav120": "https://parkrow1.wpenginepowered.com/wp-content/uploads/2025/12/private-dining-120x120.jpg",
              "fav120-width": 120,
              "fav120-height": 120,
              "fav144": "https://parkrow1.wpenginepowered.com/wp-content/uploads/2025/12/private-dining-144x144.jpg",
              "fav144-width": 144,
              "fav144-height": 144,
              "fav152": "https://parkrow1.wpenginepowered.com/wp-content/uploads/2025/12/private-dining-152x152.jpg",
              "fav152-width": 152,
              "fav152-height": 152,
              "fav180": "https://parkrow1.wpenginepowered.com/wp-content/uploads/2025/12/private-dining-180x180.jpg",
              "fav180-width": 180,
              "fav180-height": 180,
              "fav196": "https://parkrow1.wpenginepowered.com/wp-content/uploads/2025/12/private-dining-196x196.jpg",
              "fav196-width": 196,
              "fav196-height": 196,
              "gb-block-post-grid-landscape": "https://parkrow1.wpenginepowered.com/wp-content/uploads/2025/12/private-dining-600x400.jpg",
              "gb-block-post-grid-landscape-width": 600,
              "gb-block-post-grid-landscape-height": 400,
              "gb-block-post-grid-square": "https://parkrow1.wpenginepowered.com/wp-content/uploads/2025/12/private-dining-600x600.jpg",
              "gb-block-post-grid-square-width": 600,
              "gb-block-post-grid-square-height": 600
            }
          },
          "cf_stream_video": "",
          "show_controls": false,
          "yt_hover": false,
          "yt_lb": "",
          "cf_lb": "",
          "yt_start": "",
          "yt_end": "",
          "yt_aspect": "",
          "image_align": "center"
        }
      ],
      "caption": "Caption text here",
      "caption_pos": "left",
      "width": "10 columns",
      "round_corner": true,
      "corner_pos": "right",
      "align": "center",
      "push": "",
      "bleed": false,
      "content": [
        {
          "title": "Private Dining<br />\r\n& Entertaining",
          "text": "<p>An elegant setting for intimate occasions and memorable gatherings. The private dining room feels both exclusive and inviting. Whether celebrating with family or hosting among friends, every detail reflects the art of gracious living.</p>\n",
          "two_col_list": false,
          "list": "Detail list\r\nMicrowave\r\nOven\r\nGas stove\r\nHot showers\r\nTowels\r\nFree parking"
        },
        {
          "title": "Additional Amenities <br />\r\n& Services",
          "text": "<p>Concierge services, secure parking, and thoughtful conveniences make every day seamless, so residents can focus on what truly matters.</p>\n",
          "two_col_list": true,
          "list": "Detail list\r\nMicrowave\r\nOven\r\nGas stove\r\nHot showers\r\nTowels\r\nFree parking\r\nDetail list\r\nMicrowave\r\nOven\r\nGas stove\r\nHot showers\r\nTowels\r\nFree parking"
        }
      ]
    },
    {
      "acf_fc_layout": "full_bleed_img",
      "layout_settings": {
        "section_title": "",
        "section_h2": "",
        "section_text": "",
        "green_bg": false,
        "section_text_below": false
      },
      "video": [
        {
          "yt_img": {
            "ID": 89,
            "id": 89,
            "title": "bike",
            "filename": "bike.jpg",
            "filesize": 701567,
            "url": "https://parkrow1.wpenginepowered.com/wp-content/uploads/2025/12/bike.jpg",
            "link": "https://parkrow1.wpenginepowered.com/amenities/bike/",
            "alt": "",
            "author": "1",
            "description": "",
            "caption": "",
            "name": "bike",
            "status": "inherit",
            "uploaded_to": 39,
            "date": "2025-12-01 05:30:38",
            "modified": "2025-12-01 05:30:38",
            "menu_order": 0,
            "mime_type": "image/jpeg",
            "type": "image",
            "subtype": "jpeg",
            "icon": "https://parkrow1.wpenginepowered.com/wp-includes/images/media/default.png",
            "width": 1440,
            "height": 664,
            "sizes": {
              "thumbnail": "https://parkrow1.wpenginepowered.com/wp-content/uploads/2025/12/bike-150x150.jpg",
              "thumbnail-width": 150,
              "thumbnail-height": 150,
              "medium": "https://parkrow1.wpenginepowered.com/wp-content/uploads/2025/12/bike-300x138.jpg",
              "medium-width": 300,
              "medium-height": 138,
              "medium_large": "https://parkrow1.wpenginepowered.com/wp-content/uploads/2025/12/bike-768x354.jpg",
              "medium_large-width": 768,
              "medium_large-height": 354,
              "large": "https://parkrow1.wpenginepowered.com/wp-content/uploads/2025/12/bike-1024x472.jpg",
              "large-width": 1024,
              "large-height": 472,
              "1536x1536": "https://parkrow1.wpenginepowered.com/wp-content/uploads/2025/12/bike.jpg",
              "1536x1536-width": 1440,
              "1536x1536-height": 664,
              "2048x2048": "https://parkrow1.wpenginepowered.com/wp-content/uploads/2025/12/bike.jpg",
              "2048x2048-width": 1440,
              "2048x2048-height": 664,
              "header_logo": "https://parkrow1.wpenginepowered.com/wp-content/uploads/2025/12/bike-100x46.jpg",
              "header_logo-width": 100,
              "header_logo-height": 46,
              "ph": "https://parkrow1.wpenginepowered.com/wp-content/uploads/2025/12/bike-10x5.jpg",
              "ph-width": 10,
              "ph-height": 5,
              "intch_xl": "https://parkrow1.wpenginepowered.com/wp-content/uploads/2025/12/bike.jpg",
              "intch_xl-width": 1440,
              "intch_xl-height": 664,
              "intch_lg": "https://parkrow1.wpenginepowered.com/wp-content/uploads/2025/12/bike.jpg",
              "intch_lg-width": 1440,
              "intch_lg-height": 664,
              "intch_med": "https://parkrow1.wpenginepowered.com/wp-content/uploads/2025/12/bike-1000x461.jpg",
              "intch_med-width": 1000,
              "intch_med-height": 461,
              "intch_sm": "https://parkrow1.wpenginepowered.com/wp-content/uploads/2025/12/bike-600x277.jpg",
              "intch_sm-width": 600,
              "intch_sm-height": 277,
              "post_slide": "https://parkrow1.wpenginepowered.com/wp-content/uploads/2025/12/bike-750x346.jpg",
              "post_slide-width": 750,
              "post_slide-height": 346,
              "post_imgcol": "https://parkrow1.wpenginepowered.com/wp-content/uploads/2025/12/bike-400x184.jpg",
              "post_imgcol-width": 400,
              "post_imgcol-height": 184,
              "post_twocol": "https://parkrow1.wpenginepowered.com/wp-content/uploads/2025/12/bike-440x203.jpg",
              "post_twocol-width": 440,
              "post_twocol-height": 203,
              "post_slide2x": "https://parkrow1.wpenginepowered.com/wp-content/uploads/2025/12/bike.jpg",
              "post_slide2x-width": 1440,
              "post_slide2x-height": 664,
              "post_imgcol2x": "https://parkrow1.wpenginepowered.com/wp-content/uploads/2025/12/bike-800x369.jpg",
              "post_imgcol2x-width": 800,
              "post_imgcol2x-height": 369,
              "post_twocol2x": "https://parkrow1.wpenginepowered.com/wp-content/uploads/2025/12/bike-880x406.jpg",
              "post_twocol2x-width": 880,
              "post_twocol2x-height": 406,
              "logo-slider": "https://parkrow1.wpenginepowered.com/wp-content/uploads/2025/12/bike-651x300.jpg",
              "logo-slider-width": 651,
              "logo-slider-height": 300,
              "fav16": "https://parkrow1.wpenginepowered.com/wp-content/uploads/2025/12/bike-16x16.jpg",
              "fav16-width": 16,
              "fav16-height": 16,
              "fav32": "https://parkrow1.wpenginepowered.com/wp-content/uploads/2025/12/bike-32x32.jpg",
              "fav32-width": 32,
              "fav32-height": 32,
              "fav57": "https://parkrow1.wpenginepowered.com/wp-content/uploads/2025/12/bike-57x57.jpg",
              "fav57-width": 57,
              "fav57-height": 57,
              "fav60": "https://parkrow1.wpenginepowered.com/wp-content/uploads/2025/12/bike-60x60.jpg",
              "fav60-width": 60,
              "fav60-height": 60,
              "fav72": "https://parkrow1.wpenginepowered.com/wp-content/uploads/2025/12/bike-72x72.jpg",
              "fav72-width": 72,
              "fav72-height": 72,
              "fav76": "https://parkrow1.wpenginepowered.com/wp-content/uploads/2025/12/bike-76x76.jpg",
              "fav76-width": 76,
              "fav76-height": 76,
              "fav96": "https://parkrow1.wpenginepowered.com/wp-content/uploads/2025/12/bike-96x96.jpg",
              "fav96-width": 96,
              "fav96-height": 96,
              "fav114": "https://parkrow1.wpenginepowered.com/wp-content/uploads/2025/12/bike-114x114.jpg",
              "fav114-width": 114,
              "fav114-height": 114,
              "fav120": "https://parkrow1.wpenginepowered.com/wp-content/uploads/2025/12/bike-120x120.jpg",
              "fav120-width": 120,
              "fav120-height": 120,
              "fav144": "https://parkrow1.wpenginepowered.com/wp-content/uploads/2025/12/bike-144x144.jpg",
              "fav144-width": 144,
              "fav144-height": 144,
              "fav152": "https://parkrow1.wpenginepowered.com/wp-content/uploads/2025/12/bike-152x152.jpg",
              "fav152-width": 152,
              "fav152-height": 152,
              "fav180": "https://parkrow1.wpenginepowered.com/wp-content/uploads/2025/12/bike-180x180.jpg",
              "fav180-width": 180,
              "fav180-height": 180,
              "fav196": "https://parkrow1.wpenginepowered.com/wp-content/uploads/2025/12/bike-196x196.jpg",
              "fav196-width": 196,
              "fav196-height": 196,
              "gb-block-post-grid-landscape": "https://parkrow1.wpenginepowered.com/wp-content/uploads/2025/12/bike-600x400.jpg",
              "gb-block-post-grid-landscape-width": 600,
              "gb-block-post-grid-landscape-height": 400,
              "gb-block-post-grid-square": "https://parkrow1.wpenginepowered.com/wp-content/uploads/2025/12/bike-600x600.jpg",
              "gb-block-post-grid-square-width": 600,
              "gb-block-post-grid-square-height": 600
            }
          },
          "cf_stream_video": "https://customer-u7ssw6pfj8oowdhj.cloudflarestream.com/e2e872dc101b4f9e32540ff5c4487d63/manifest/video.m3u8",
          "show_controls": false,
          "yt_hover": false,
          "yt_lb": "",
          "cf_lb": "",
          "yt_start": "",
          "yt_end": "",
          "yt_aspect": "",
          "image_align": "center"
        }
      ],
      "caption": "",
      "caption_pos": "",
      "width": "full",
      "round_corner": false,
      "corner_pos": "left",
      "align": "",
      "push": "",
      "bleed": true,
      "content": false
    }
  ],
  "_syncedAt": "2025-12-04 22:49:06"
}